SageNP/SageNP.py
SageNP/__init__.py
sagenp-0.6.dist-info/licenses/LICENSE
sagenp-0.6.dist-info/METADATA
sagenp-0.6.dist-info/WHEEL
sagenp-0.6.dist-info/top_level.txt
sagenp-0.6.dist-info/RECORD
