Metadata-Version: 2.4
Name: SageNP
Version: 0.6
Summary: Newman-Penrose calculations for SageMath
Home-page: https://github.com/tbirkandan/SageNP
Author: Tolga Birkandan, Onur Arman, Emir Baysazan, Selinay Sude Binici, Pelin Ozturk, Efe Ozyurek
Author-email: birkandant@itu.edu.tr
Keywords: SageMath,Newman-Penrose formalism,Petrov classification
Classifier: Programming Language :: Python :: 3
Classifier: License :: OSI Approved :: GNU General Public License v2 or later (GPLv2+)
Classifier: Operating System :: OS Independent
Classifier: Topic :: Scientific/Engineering :: Mathematics
Classifier: Topic :: Scientific/Engineering :: Physics
License-File: LICENSE
Dynamic: author
Dynamic: author-email
Dynamic: classifier
Dynamic: description
Dynamic: description-content-type
Dynamic: home-page
Dynamic: keywords
Dynamic: license-file
Dynamic: summary
